roh_pipelines/__init__.py
roh_pipelines/clone_environment.py
roh_pipelines_clone_environment-1.1.0.dist-info/LICENSE
roh_pipelines_clone_environment-1.1.0.dist-info/METADATA
roh_pipelines_clone_environment-1.1.0.dist-info/WHEEL
roh_pipelines_clone_environment-1.1.0.dist-info/entry_points.txt
roh_pipelines_clone_environment-1.1.0.dist-info/top_level.txt
roh_pipelines_clone_environment-1.1.0.dist-info/RECORD
